py_jama_rest_client/__init__.py
py_jama_rest_client/client.py
py_jama_rest_client/core.py
py_jama_rest_client-1.17.1.dist-info/LICENSE.txt
py_jama_rest_client-1.17.1.dist-info/METADATA
py_jama_rest_client-1.17.1.dist-info/WHEEL
py_jama_rest_client-1.17.1.dist-info/top_level.txt
py_jama_rest_client-1.17.1.dist-info/RECORD
