Metadata-Version: 2.1
Name: py-jama-rest-client
Version: 1.17.1
Summary: A client for the Jama Connect REST API
Home-page: https://github.com/JamaSoftware/py-jama-rest-client
Author: Nick McHale
Author-email: nmchale@jamasoftware.com
License: MIT
Project-URL: Bug Reports, https://github.com/JamaSoftware/py-jama-rest-client/issues
Project-URL: Source, https://github.com/JamaSoftware/py-jama-rest-client
Project-URL: Jama Software, https://www.jamasoftware.com
Project-URL: Jama Developer resources, https://dev.jamasoftware.com
Keywords: REST Client
Classifier: Development Status :: 4 - Beta
Classifier: Intended Audience :: Developers
Classifier: Topic :: Software Development :: Libraries
Classifier: License :: OSI Approved :: MIT License
Classifier: Programming Language :: Python :: 3.7
License-File: LICENSE.txt
